procuret/__init__.py
procuret/session.py
procuret/version.py
procuret/address/__init__.py
procuret/address/address.py
procuret/ancillary/__init__.py
procuret/ancillary/abstract_session.py
procuret/ancillary/command_line.py
procuret/ancillary/communication_option.py
procuret/ancillary/entity_headline.py
procuret/ancillary/sale_nomenclature.py
procuret/ancillary/session_lifecycle.py
procuret/ancillary/session_perspective.py
procuret/commitment/__init__.py
procuret/commitment/commitment.py
procuret/country/__init__.py
procuret/country/country.py
procuret/customer_payment/__init__.py
procuret/customer_payment/payment.py
procuret/data/__init__.py
procuret/data/codable.py
procuret/data/decodable.py
procuret/data/disposition.py
procuret/data/order.py
procuret/email_address/__init__.py
procuret/email_address/address.py
procuret/entity/__init__.py
procuret/entity/entity.py
procuret/entity_id_type/__init__.py
procuret/entity_id_type/type.py
procuret/entity_identifier/__init__.py
procuret/entity_identifier/identifier.py
procuret/errors/__init__.py
procuret/errors/api_error.py
procuret/errors/error.py
procuret/errors/inconsistent.py
procuret/errors/type_error.py
procuret/global_brand/__init__.py
procuret/global_brand/brand.py
procuret/global_brand/selection.py
procuret/http/__init__.py
procuret/http/api_request.py
procuret/http/method.py
procuret/http/query_parameter.py
procuret/http/query_parameters.py
procuret/human/__init__.py
procuret/human/headline.py
procuret/human/human.py
procuret/human_identity/__init__.py
procuret/human_identity/identity.py
procuret/human_identity_document/__init__.py
procuret/human_identity_document/document.py
procuret/human_identity_document/state.py
procuret/human_identity_document/type.py
procuret/instalment_line/__init__.py
procuret/instalment_line/line.py
procuret/instalment_link/__init__.py
procuret/instalment_link/instalment_link.py
procuret/instalment_link/open.py
procuret/instalment_schedule/__init__.py
procuret-0.0.45.dist-info/LICENSE
procuret-0.0.45.dist-info/METADATA
procuret-0.0.45.dist-info/WHEEL
procuret-0.0.45.dist-info/top_level.txt
procuret-0.0.45.dist-info/RECORD
